{
    "1": "ประชากรจากการทะเบียน จำแนกตามกลุ่มอายุและเพศ พ.ศ.2566",
    "2": "ประชากรอายุ 15 ปีขึ้นไป จำแนกตามสถานภาพแรงงานและเพศ ไตรมาส 3 พ.ศ. 2565 - 2566 และ อัตราการว่างงาน จำแนกตามกลุ่มอายุและระดับการศึกษาที่สำเร็จ ไตรมาส 3 พ.ศ. 2565 - 2566",
    "3": "จำนวนและร้อยละของนักเรียน นิสิต นักศึกษาในระบบโรงเรียนต่อประชากรในวัยเรียน ปีการศึกษา 2565",
    "4": "วัดในศาสนาพุทธ จำแนกตามภาค พ.ศ. 2566",
    "5": "การตาย จำแนกตามลำดับของกลุ่มสาเหตุการตาย 10 กลุ่มแรก (ตามบัญชี จำแนกโรคระหว่างประเทศ ฉบับแก้ไขครั้งที่ 10) พ.ศ.2565",
    "6": "ร้อยละของประชากรที่มีสวัสดิการค่ารักษาพยาบาล จำแนกตามประเภทสวัสดิการค่ารักษาพยาบาล พ.ศ. 2566 และ สัดส่วนของผู้จำนำ จำแนกตามกลุ่มอาชีพ และทรัพย์จำนำ ปีงบประมาณ 2566",
    "7": "จำนวนและสัดส่วนผู้สูงอายุที่ทำงาน จำแนกตามภาคและเพศ พ.ศ. 2566",
    "8": "ร้อยละของรายได้ ค่าใช้จ่ายเฉลี่ยต่อเดือน และจำนวนหนี้สินเฉลี่ยต่อครัวเรือนทั้งสิ้น พ.ศ.2566",
    "9": "อันดับคดีแพ่งและคดีอาญาที่ขึ้นสู่การพิจารณาของศาลชั้นต้น พ.ศ. 2566 และ คดีเด็กและเยาวชนที่ถูกดำเนินคดี โดยสถานพินิจฯ จำแนกตามเพศ และฐานความผิด พ.ศ. 2566",
    "10": "ผลิตภัณฑ์มวลรวมในประเทศ พ.ศ. 2565",
    "11": "จังหวัดที่อนุญาตให้ฆ่าสัตว์เป็นอาหารมากที่สุด จําแนกตามชนิด พ.ศ. 2566",
    "12": "โรงงานอุตสาหกรรมที่จดทะเบียนไว้กับกระทรวงอุตสาหกรรมและได้รับอนุญาตให้ประกอบกิจการ(ตามพระราชบัญญัติโรงงาน พ.ศ. 2535) จำแนกตามภาค พ.ศ. 2566 และ คนทำงานในโรงงานอุตสาหกรรม จำแนกตามเพศ และภาค พ.ศ. 2566",
    "13": "การใช้พลังงานในสาขาอุตสาหกรรมการผลิต จำแนกตามประเภทพลังงาน พ.ศ.2565 และ การใช้พลังงานไฟฟ้า จำแนกตามสาขาเศรษฐกิจ พ.ศ.2563-2565",
    "14": "มูลค่าสินค้าขาเข้าและขาออก พ.ศ. 2557 - 2566 และ อัตราเงินเฟ้อทั่วไป พ.ศ. 2565 - 2566",
    "15": "อันดับรถจดทะเบียนใหม่ (ตามพระราชบัญญัติรถยนต์ พ.ศ.2522) พ.ศ.2566 และ อันดับรถจดทะเบียนใหม่ (ตามพระราชบัญญัติการขนส่งทางบก พ.ศ.2522) พ.ศ.2566",
    "16": "บริการไปรษณีย์ พ.ศ. 2560 - 2566",
    "17": "ข้อมูลของสถานประกอบการที่พักแรม พ.ศ. 2562 และ 2564",
    "18": "จำนวนบัตรพลาสติก พ.ศ. 2562-2566 และ ธุรกรรมการชำระเงินผ่านบริการ Mobile Banking พ.ศ. 2562 - 2566",
    "19": "งบประมาณรายจ่าย จำแนกตามกลุ่มงบประมาณ ปีงบประมาณ 2567 และ การจัดสรรงบประมาณ จำแนกตามงบรายจ่าย ปีงบประมาณ 2567",
    "20": "การจดแจ้งลิขสิทธิ์ จําแนกตามประเภทของงาน พ.ศ. 2565 – 2566",
    "21": "ปริมาณน้ำในอ่างเก็บน้ำขนาดใหญ่ ณ วันที่ 1 มกราคม พ.ศ. 2567"
}
